.DS_Store
build/.DS_Store
build/lib/.DS_Store
build/lib/build/lib/build/lib/build/lib/fif/gif_codec.py
build/lib/build/lib/build/lib/build/lib/fif/main.py
build/lib/build/lib/build/lib/build/lib/fif/png_codec.py
build/lib/build/lib/build/lib/build/lib/fif/tools.py
build/lib/build/lib/build/lib/build/lib/fif/wav_codec.py
build/lib/build/lib/build/lib/fif/gif_codec.py
build/lib/build/lib/build/lib/fif/main.py
build/lib/build/lib/build/lib/fif/png_codec.py
build/lib/build/lib/build/lib/fif/tools.py
build/lib/build/lib/build/lib/fif/wav_codec.py
build/lib/build/lib/fif/gif_codec.py
build/lib/build/lib/fif/main.py
build/lib/build/lib/fif/png_codec.py
build/lib/build/lib/fif/tools.py
build/lib/build/lib/fif/wav_codec.py
build/lib/fif/gif_codec.py
build/lib/fif/main.py
build/lib/fif/png_codec.py
build/lib/fif/tools.py
build/lib/fif/wav_codec.py
fif/gif_codec.py
fif/main.py
fif/png_codec.py
fif/tools.py
fif/wav_codec.py
fif-1.3.1.dist-info/LICENSE
fif-1.3.1.dist-info/METADATA
fif-1.3.1.dist-info/WHEEL
fif-1.3.1.dist-info/entry_points.txt
fif-1.3.1.dist-info/top_level.txt
fif-1.3.1.dist-info/RECORD
