Metadata-Version: 2.1
Name: fif
Version: 1.3.1
Summary: A command line tool for embedding any file into PNG, GIF, WAV file formats and decoding back.
Home-page: https://github.com/hazarek/fif
Author: Hazar
License: UNKNOWN
Platform: UNKNOWN
Classifier: Topic :: Utilities
Classifier: Programming Language :: Python :: 3
Classifier: Programming Language :: Python :: 3.5
Classifier: Programming Language :: Python :: 3.6
Classifier: Programming Language :: Python :: 3.7
Classifier: Programming Language :: Python :: 3.8
Classifier: Programming Language :: Python :: 3.9
Requires-Python: >=3
Requires-Dist: Pillow (>=8.0.0)
Requires-Dist: filetype (>=1.0.7)
